test_module.cp37-win32.pyd
test_module_railgun-0.4.dist-info/METADATA
test_module_railgun-0.4.dist-info/WHEEL
test_module_railgun-0.4.dist-info/top_level.txt
test_module_railgun-0.4.dist-info/RECORD
