Metadata-Version: 2.1
Name: test-module-railgun
Version: 0.4
Summary: A  module for test
Home-page: https://github.com/vfrtgb158/email
Author: railgun
Author-email: GenshinImpactRailgun@gmail.com
License: MIT
Platform: UNKNOWN
